{"spider_44_01_001.png": {"size": [121.0, 106.0], "offset": [2.0, 4.0], "location": [1.0, 1.0], "rotated": true}, "spider_44_01_2_001.png": {"size": [113.0, 98.0], "offset": [2.0, 4.0], "location": [242.0, 1.0], "rotated": true}, "spider_44_01_extra_001.png": {"size": [109.0, 66.0], "offset": [2.0, 19.0], "location": [342.0, 1.0], "rotated": true}, "spider_44_01_glow_001.png": {"size": [131.0, 114.0], "offset": [2.0, 4.0], "location": [109.0, 1.0], "rotated": false}, "spider_44_02_001.png": {"size": [45.0, 62.0], "offset": [0.0, 0.0], "location": [468.0, 77.0], "rotated": true}, "spider_44_02_2_001.png": {"size": [37.0, 56.0], "offset": [0.0, 0.0], "location": [410.0, 85.0], "rotated": true}, "spider_44_02_glow_001.png": {"size": [53.0, 70.0], "offset": [0.0, 0.0], "location": [510.0, 1.0], "rotated": false}, "spider_44_03_001.png": {"size": [44.0, 74.0], "offset": [0.0, 0.0], "location": [464.0, 1.0], "rotated": false}, "spider_44_03_2_001.png": {"size": [38.0, 66.0], "offset": [0.0, 0.0], "location": [565.0, 1.0], "rotated": true}, "spider_44_03_glow_001.png": {"size": [52.0, 82.0], "offset": [0.0, 0.0], "location": [410.0, 1.0], "rotated": false}, "spider_44_04_001.png": {"size": [55.0, 34.0], "offset": [0.0, 0.0], "location": [564.0, 85.0], "rotated": false}, "spider_44_04_2_001.png": {"size": [29.0, 30.0], "offset": [9.0, 0.0], "location": [532.0, 73.0], "rotated": true}, "spider_44_04_glow_001.png": {"size": [63.0, 42.0], "offset": [0.0, 0.0], "location": [565.0, 41.0], "rotated": false}}